ionoscloud_dataplatform/__init__.py
ionoscloud_dataplatform/api_client.py
ionoscloud_dataplatform/configuration.py
ionoscloud_dataplatform/exceptions.py
ionoscloud_dataplatform/rest.py
ionoscloud_dataplatform/api/__init__.py
ionoscloud_dataplatform/api/data_platform_cluster_api.py
ionoscloud_dataplatform/api/data_platform_meta_data_api.py
ionoscloud_dataplatform/api/data_platform_node_pool_api.py
ionoscloud_dataplatform/models/__init__.py
ionoscloud_dataplatform/models/availability_zone.py
ionoscloud_dataplatform/models/cluster.py
ionoscloud_dataplatform/models/cluster_list_response_data.py
ionoscloud_dataplatform/models/cluster_response_data.py
ionoscloud_dataplatform/models/create_cluster_properties.py
ionoscloud_dataplatform/models/create_cluster_request.py
ionoscloud_dataplatform/models/create_node_pool_properties.py
ionoscloud_dataplatform/models/create_node_pool_request.py
ionoscloud_dataplatform/models/error_message.py
ionoscloud_dataplatform/models/error_response.py
ionoscloud_dataplatform/models/maintenance_window.py
ionoscloud_dataplatform/models/metadata.py
ionoscloud_dataplatform/models/node_pool.py
ionoscloud_dataplatform/models/node_pool_list_response_data.py
ionoscloud_dataplatform/models/node_pool_response_data.py
ionoscloud_dataplatform/models/patch_cluster_properties.py
ionoscloud_dataplatform/models/patch_cluster_request.py
ionoscloud_dataplatform/models/patch_node_pool_properties.py
ionoscloud_dataplatform/models/patch_node_pool_request.py
ionoscloud_dataplatform/models/storage_type.py
ionoscloud_dataplatform-1.0.0.dist-info/LICENSE
ionoscloud_dataplatform-1.0.0.dist-info/METADATA
ionoscloud_dataplatform-1.0.0.dist-info/WHEEL
ionoscloud_dataplatform-1.0.0.dist-info/top_level.txt
ionoscloud_dataplatform-1.0.0.dist-info/RECORD
